enzona_api/__init__.py
enzona_api/enzona_api.py
enzona_api/enzona_business_payment.py
enzona_api/error.py
enzona_api/responses.py
enzona_api-0.1.2.2.dist-info/LICENSE
enzona_api-0.1.2.2.dist-info/METADATA
enzona_api-0.1.2.2.dist-info/WHEEL
enzona_api-0.1.2.2.dist-info/top_level.txt
enzona_api-0.1.2.2.dist-info/RECORD
