Metadata-Version: 2.1
Name: enzona-api
Version: 0.1.2.2
Summary: Enzona's payment platform API access library
Home-page: https://github.com/MoonMagiCreation/enzona_api
Author: Josué Carballo Baños
Author-email: josueccb@yandex.com
License: GPL 3.0
Classifier: Programming Language :: Python :: 3
Classifier: License :: OSI Approved :: GNU General Public License v3 or later (GPLv3+)
Requires-Python: >=3.5
License-File: LICENSE
Requires-Dist: requests (>=2.23.0)
Requires-Dist: bs4 (>=0.0.1)
Requires-Dist: qrcode (>=6.1)
